[
  {
    "id": "1",
    "netlify": "https://silver-profiterole-7224fd.netlify.app/",
    "github": "https://github.com/JosefineEngdahl/project-weather-app",
    "title": "Weather app",
    "description": "Responsive website connected with weather API",
    "image": "images/weather-app.jpg",
    "tags": [
      "API",
      "HTML",
      "CSS",
      "Javascript"
    ]
  },
  {
    "id": "2",
    "netlify": "https://the-music-release-project.netlify.app/",
    "github": "https://github.com/Technigo/project-music-releases/pull/221?",
    "title": "Music page",
    "description": "Responsive music release page made using React",
    "image": "./music-releases.jpg",
    "tags": [
      "React",
      "HTML",
      "CSS",
      "Javascript"
    ]
  }
]